setup.py
raipy/Constant.py
raipy/Controller.py
raipy/DragAndDrop.py
raipy/DragAndDrop2.py
raipy/DragAndDrop3.py
raipy/Example.py
raipy/FileManager.py
raipy/GUI.py
raipy/GpibInst.py
raipy/GraphManager.py
raipy/Help.py
raipy/LCD_Display.py
raipy/MyPyqtGraph.py
raipy/Time.py
raipy/UserClassBase.py
raipy/__init__.py
raipy/template.py
raipy/temporary.py
raipy.egg-info/PKG-INFO
raipy.egg-info/SOURCES.txt
raipy.egg-info/dependency_links.txt
raipy.egg-info/requires.txt
raipy.egg-info/top_level.txt
raipy/Examples/Demo.py
raipy/Examples/GPIB_query.py
raipy/Examples/Lines.py
raipy/Icons/logo.png