Metadata-Version: 1.1
Name: raipy
Version: 0.5
Summary: GUI for measurements
Home-page: https://github.com/threemeninaboat3247/raipy
Author: Yuki Arai
Author-email: threemeninaboat3247@gmail.com
License: MIT
Keywords: GUI
Platform: UNKNOWN
Classifier: Programming Language :: Python :: 3.5
Classifier: Intended Audience :: Science/Research
Classifier: License :: OSI Approved :: MIT License
